genotype_json_tree/__init__.py
genotype_json_tree/json.py
genotype_json_tree/py.typed
genotype_json_tree-0.2.0.dist-info/METADATA
genotype_json_tree-0.2.0.dist-info/WHEEL
genotype_json_tree-0.2.0.dist-info/RECORD
