Metadata-Version: 2.3
Name: genotype-json-tree
Version: 0.2.0
Summary: Genotype language JSON tree
License: MIT
Author: Sasha Koss
Author-email: koss@nocorp.me
Requires-Python: >=3.8,<4.0
Classifier: License :: OSI Approved :: MIT License
Classifier: Programming Language :: Python :: 3
Classifier: Programming Language :: Python :: 3.8
Classifier: Programming Language :: Python :: 3.9
Classifier: Programming Language :: Python :: 3.10
Classifier: Programming Language :: Python :: 3.11
Classifier: Programming Language :: Python :: 3.12
Classifier: Programming Language :: Python :: 3.13
Requires-Dist: genotype-runtime (>=0.4,<0.5)
